LICENSE
MANIFEST.in
README
README.rst
requirements.txt
setup.py
k/__init__.py
k.egg-info/PKG-INFO
k.egg-info/SOURCES.txt
k.egg-info/dependency_links.txt
k.egg-info/top_level.txt