Metadata-Version: 1.1
Name: k
Version: 0.0.1
Summary: enums for Python
Home-page: https://github.com/bfontaine/k
Author: Baptiste Fontaine
Author-email: b@ptistefontaine.fr
License: Copyright © 2015 – Baptiste Fontaine
